Workbook
Name IQ_CH: 110000
Name IQ_CQ: 5000
Name IQ_CY: 10000
Name IQ_DAILY: 500000
Name IQ_FH: 100000
Name IQ_FQ: 500
Name IQ_FY: 1000
Name IQ_LTM: 2000
Name IQ_MONTH: 15000
Name IQ_NTM: 6000
Name IQ_WEEK: 50000
Name IQ_YTD: 3000

Sheet Discount Definitions
A1: Water Sensor
A2: Y - Yes
A3: N - No
A5: Alarm
A6: 1 - None
A7: 2 - Local Alarm
A8: 3 - High Tech Local Alarm
A9: 4 - Monitored High Tech Alarm
A11: Roof Type
A12: 1 - Composite Shingle
A13: 2 - Hail Resistant Shingle
A14: 3 - Solar Panel over Shingle
... A19: 3) Some perils may not be impacted by discounts.

Sheet Premiums
A1: Discounts | D1: Peril
A2: Water Sensor | B2: Alarm | C2: Roof Type | D2: Wind/Hail | E2: Water | F2: Fire | G2: Theft | H2: Other | I2: Liability
A3: Y | B3: 1 | C3: 1 | D3: 2521391 | E3: 1119379 | F3: 836869 | G3: 280509 | H3: 562613 | I3: 279939
A4: Y | B4: 1 | C4: 2 | D4: 1265040 | E4: 558693 | F4: 418395 | G4: 139599 | H4: 280331 | I4: 139547
A5: Y | B5: 1 | C5: 3 | D5: 421834 | E5: 186303 | F5: 139468 | G5: 46769 | H5: 93730 | I5: 46508
A6: Y | B6: 2 | C6: 1 | D6: 10104346 | E6: 4488414 | F6: 3371550 | G6: 1124858 | H6: 2245941 | I6: 1117251
A7: Y | B7: 2 | C7: 2 | D7: 5037886 | E7: 2236519 | F7: 1679608 | G7: 558983 | H7: 1118357 | I7: 562623
A8: Y | B8: 2 | C8: 3 | D8: 1674055 | E8: 750153 | F8: 560756 | G8: 187399 | H8: 371994 | I8: 186625
A9: Y | B9: 3 | C9: 1 | D9: 7574980 | E9: 3370715 | F9: 2522123 | G9: 836747 | H9: 1679515 | I9: 836211
A10: Y | B10: 3 | C10: 2 | D10: 3780117 | E10: 1678581 | F10: 1261442 | G10: 419991 | H10: 842585 | I10: 417989
A11: Y | B11: 3 | C11: 3 | D11: 1263122 | E11: 560406 | F11: 420443 | G11: 139692 | H11: 278698 | I11: 140219
A12: Y | B12: 4 | C12: 1 | D12: 5055839 | E12: 2231941 | F12: 1683337 | G12: 558913 | H12: 1116047 | I12: 558250
A13: Y | B13: 4 | C13: 2 | D13: 2529833 | E13: 1115315 | F13: 837676 | G13: 279468 | H13: 560065 | I13: 281288
A14: Y | B14: 4 | C14: 3 | D14: 842100 | E14: 372260 | F14: 278614 | G14: 93021 | H14: 186793 | I14: 93263
... A26: N | B26: 4 | C26: 3 | D26: 3362025 | E26: 1495265 | F26: 1125110 | G26: 374271 | H26: 747189 | I26: 373847
D27: =SUM(D3:D26) -> 209852582 | E27: =SUM(E3:E26) -> 93297247 | F27: =SUM(F3:F26) -> 70067125 | G27: =SUM(G3:G26) -> 23333539 | H27: =SUM(H3:H26) -> 46690073 | I27: =SUM(I3:I26) -> 23324942

Sheet Losses and LAE
A1: Discounts | D1: Peril
A2: Water Sensor | B2: Alarm | C2: Roof Type | D2: Wind/Hail | E2: Water | F2: Fire | G2: Theft | H2: Other | I2: Liability
A3: Y | B3: 1 | C3: 1 | D3: 1726774 | E3: 556803 | F3: 549047 | G3: 185052 | H3: 380660 | I3: 185038
A4: Y | B4: 1 | C4: 2 | D4: 662984 | E4: 285231 | F4: 283785 | G4: 92461 | H4: 189308 | I4: 95223
A5: Y | B5: 1 | C5: 3 | D5: 228601 | E5: 94733 | F5: 92825 | G5: 31663 | H5: 64078 | I5: 31197
A6: Y | B6: 2 | C6: 1 | D6: 6654041 | E6: 1915849 | F6: 1945692 | G6: 649133 | H6: 1515901 | I6: 747175
A7: Y | B7: 2 | C7: 2 | D7: 2698878 | E7: 946853 | F7: 948775 | G7: 317254 | H7: 744221 | I7: 382191
A8: Y | B8: 2 | C8: 3 | D8: 888879 | E8: 314025 | F8: 313157 | G8: 106563 | H8: 246013 | I8: 125879
A9: Y | B9: 3 | C9: 1 | D9: 4976090 | E9: 1210034 | F9: 1185977 | G9: 395897 | H9: 1141583 | I9: 559132
A10: Y | B10: 3 | C10: 2 | D10: 2050099 | E10: 578116 | F10: 580529 | G10: 194549 | H10: 573169 | I10: 273887
A11: Y | B11: 3 | C11: 3 | D11: 668719 | E11: 196149 | F11: 198781 | G11: 65618 | H11: 182625 | I11: 93338
A12: Y | B12: 4 | C12: 1 | D12: 3426463 | E12: 668771 | F12: 677297 | G12: 226753 | H12: 745281 | I12: 372428
A13: Y | B13: 4 | C13: 2 | D13: 1330541 | E13: 335603 | F13: 339271 | G13: 112551 | H13: 374785 | I13: 189737
A14: Y | B14: 4 | C14: 3 | D14: 443077 | E14: 114217 | F14: 114156 | G14: 37254 | H14: 125916 | I14: 62799
... A26: N | B26: 4 | C26: 3 | D26: 1825875 | E26: 1020460 | F26: 449680 | G26: 148447 | H26: 506203 | I26: 247982

Sheet Loss Ratios
A1: Discounts | D1: Peril
A2: Water Sensor | B2: Alarm | C2: Roof Type | D2: Wind/Hail | E2: Water | F2: Fire | G2: Theft | H2: Other | I2: Liability
A3: Y | B3: 1 | C3: 1 | D3: ='Losses and LAE'!D3/Premiums!D3 -> 0.68484975 | E3: ='Losses and LAE'!E3/Premiums!E3 -> 0.49742134 | F3: ='Losses and LAE'!F3/Premiums!F3 -> 0.65607281 | G3: ='Losses and LAE'!G3/Premiums!G3 -> 0.65970076 | H3: ='Losses and LAE'!H3/Premiums!H3 -> 0.67659297 | I3: ='Losses and LAE'!I3/Premiums!I3 -> 0.660994
A4: Y | B4: 1 | C4: 2 | D4: ='Losses and LAE'!D4/Premiums!D4 -> 0.52408145 | E4: ='Losses and LAE'!E4/Premiums!E4 -> 0.51053262 | F4: ='Losses and LAE'!F4/Premiums!F4 -> 0.67827053 | G4: ='Losses and LAE'!G4/Premiums!G4 -> 0.66233282 | H4: ='Losses and LAE'!H4/Premiums!H4 -> 0.6753017 | I4: ='Losses and LAE'!I4/Premiums!I4 -> 0.68237225
A5: Y | B5: 1 | C5: 3 | D5: ='Losses and LAE'!D5/Premiums!D5 -> 0.5419217 | E5: ='Losses and LAE'!E5/Premiums!E5 -> 0.50848886 | F5: ='Losses and LAE'!F5/Premiums!F5 -> 0.66556486 | G5: ='Losses and LAE'!G5/Premiums!G5 -> 0.67700827 | H5: ='Losses and LAE'!H5/Premiums!H5 -> 0.68364451 | I5: ='Losses and LAE'!I5/Premiums!I5 -> 0.67078782
A6: Y | B6: 2 | C6: 1 | D6: ='Losses and LAE'!D6/Premiums!D6 -> 0.65853258 | E6: ='Losses and LAE'!E6/Premiums!E6 -> 0.4268432 | F6: ='Losses and LAE'!F6/Premiums!F6 -> 0.57709125 | G6: ='Losses and LAE'!G6/Premiums!G6 -> 0.57707995 | H6: ='Losses and LAE'!H6/Premiums!H6 -> 0.67495139 | I6: ='Losses and LAE'!I6/Premiums!I6 -> 0.66876199
A7: Y | B7: 2 | C7: 2 | D7: ='Losses and LAE'!D7/Premiums!D7 -> 0.53571637 | E7: ='Losses and LAE'!E7/Premiums!E7 -> 0.42336014 | F7: ='Losses and LAE'!F7/Premiums!F7 -> 0.56487883 | G7: ='Losses and LAE'!G7/Premiums!G7 -> 0.56755572 | H7: ='Losses and LAE'!H7/Premiums!H7 -> 0.66545924 | I7: ='Losses and LAE'!I7/Premiums!I7 -> 0.67930213
A8: Y | B8: 2 | C8: 3 | D8: ='Losses and LAE'!D8/Premiums!D8 -> 0.53097359 | E8: ='Losses and LAE'!E8/Premiums!E8 -> 0.4186146 | F8: ='Losses and LAE'!F8/Premiums!F8 -> 0.55845501 | G8: ='Losses and LAE'!G8/Premiums!G8 -> 0.56864231 | H8: ='Losses and LAE'!H8/Premiums!H8 -> 0.66133594 | I8: ='Losses and LAE'!I8/Premiums!I8 -> 0.67450234
A9: Y | B9: 3 | C9: 1 | D9: ='Losses and LAE'!D9/Premiums!D9 -> 0.65691131 | E9: ='Losses and LAE'!E9/Premiums!E9 -> 0.35898437 | F9: ='Losses and LAE'!F9/Premiums!F9 -> 0.47022964 | G9: ='Losses and LAE'!G9/Premiums!G9 -> 0.47313824 | H9: ='Losses and LAE'!H9/Premiums!H9 -> 0.67970992 | I9: ='Losses and LAE'!I9/Premiums!I9 -> 0.66864942
A10: Y | B10: 3 | C10: 2 | D10: ='Losses and LAE'!D10/Premiums!D10 -> 0.54233745 | E10: ='Losses and LAE'!E10/Premiums!E10 -> 0.34440757 | F10: ='Losses and LAE'!F10/Premiums!F10 -> 0.46021062 | G10: ='Losses and LAE'!G10/Premiums!G10 -> 0.46322183 | H10: ='Losses and LAE'!H10/Premiums!H10 -> 0.68025066 | I10: ='Losses and LAE'!I10/Premiums!I10 -> 0.6552493
A11: Y | B11: 3 | C11: 3 | D11: ='Losses and LAE'!D11/Premiums!D11 -> 0.52941759 | E11: ='Losses and LAE'!E11/Premiums!E11 -> 0.35001231 | F11: ='Losses and LAE'!F11/Premiums!F11 -> 0.47278941 | G11: ='Losses and LAE'!G11/Premiums!G11 -> 0.46973341 | H11: ='Losses and LAE'!H11/Premiums!H11 -> 0.65527919 | I11: ='Losses and LAE'!I11/Premiums!I11 -> 0.66565872
A12: Y | B12: 4 | C12: 1 | D12: ='Losses and LAE'!D12/Premiums!D12 -> 0.67772391 | E12: ='Losses and LAE'!E12/Premiums!E12 -> 0.2996365 | F12: ='Losses and LAE'!F12/Premiums!F12 -> 0.40235378 | G12: ='Losses and LAE'!G12/Premiums!G12 -> 0.40570357 | H12: ='Losses and LAE'!H12/Premiums!H12 -> 0.66778639 | I12: ='Losses and LAE'!I12/Premiums!I12 -> 0.6671348
A13: Y | B13: 4 | C13: 2 | D13: ='Losses and LAE'!D13/Premiums!D13 -> 0.52594025 | E13: ='Losses and LAE'!E13/Premiums!E13 -> 0.30090423 | F13: ='Losses and LAE'!F13/Premiums!F13 -> 0.40501459 | G13: ='Losses and LAE'!G13/Premiums!G13 -> 0.40273305 | H13: ='Losses and LAE'!H13/Premiums!H13 -> 0.66918126 | I13: ='Losses and LAE'!I13/Premiums!I13 -> 0.67452931
A14: Y | B14: 4 | C14: 3 | D14: ='Losses and LAE'!D14/Premiums!D14 -> 0.52615723 | E14: ='Losses and LAE'!E14/Premiums!E14 -> 0.3068205 | F14: ='Losses and LAE'!F14/Premiums!F14 -> 0.40972815 | G14: ='Losses and LAE'!G14/Premiums!G14 -> 0.40049021 | H14: ='Losses and LAE'!H14/Premiums!H14 -> 0.67409378 | I14: ='Losses and LAE'!I14/Premiums!I14 -> 0.67335385
... A26: N | B26: 4 | C26: 3 | D26: ='Losses and LAE'!D26/Premiums!D26 -> 0.54308787 | E26: ='Losses and LAE'!E26/Premiums!E26 -> 0.68246097 | F26: ='Losses and LAE'!F26/Premiums!F26 -> 0.39967648 | G26: ='Losses and LAE'!G26/Premiums!G26 -> 0.39662971 | H26: ='Losses and LAE'!H26/Premiums!H26 -> 0.67747652 | I26: ='Losses and LAE'!I26/Premiums!I26 -> 0.66332484

Sheet Claim&Credibility
A1: Discounts | D1: Peril
A2: Water Sensor | B2: Alarm | C2: Roof Type | D2: Wind/Hail | E2: Water | F2: Fire | G2: Theft | H2: Other | I2: Liability
A3: Y | B3: 1 | C3: 1 | D3: 60 | E3: 72 | F3: 23 | G3: 18 | H3: 110 | I3: 1
A4: Y | B4: 1 | C4: 2 | D4: 27 | E4: 37 | F4: 9 | G4: 9 | H4: 58 | I4: 1
A5: Y | B5: 1 | C5: 3 | D5: 12 | E5: 9 | F5: 3 | G5: 6 | H5: 18 | I5: 1
A6: Y | B6: 2 | C6: 1 | D6: 548 | E6: 186 | F6: 79 | G6: 72 | H6: 352 | I6: 4
A7: Y | B7: 2 | C7: 2 | D7: 103 | E7: 87 | F7: 63 | G7: 27 | H7: 108 | I7: 2
A8: Y | B8: 2 | C8: 3 | D8: 73 | E8: 20 | F8: 15 | G8: 8 | H8: 37 | I8: 1
A9: Y | B9: 3 | C9: 1 | D9: 408 | E9: 92 | F9: 42 | G9: 29 | H9: 330 | I9: 7
A10: Y | B10: 3 | C10: 2 | D10: 103 | E10: 75 | F10: 24 | G10: 41 | H10: 120 | I10: 3
A11: Y | B11: 3 | C11: 3 | D11: 25 | E11: 23 | F11: 6 | G11: 8 | H11: 41 | I11: 1
A12: Y | B12: 4 | C12: 1 | D12: 168 | E12: 83 | F12: 48 | G12: 17 | H12: 119 | I12: 3
A13: Y | B13: 4 | C13: 2 | D13: 72 | E13: 20 | F13: 10 | G13: 11 | H13: 84 | I13: 1
A14: Y | B14: 4 | C14: 3 | D14: 18 | E14: 18 | F14: 5 | G14: 4 | H14: 19 | I14: 1
... A26: N | B26: 4 | C26: 3 | D26: 58 | E26: 59 | F26: 11 | G26: 27 | H26: 76 | I26: 1
A28: Segment Credibility
A30: Hazards | B30: Discount | C30: Claim Number | E30: Partial Credibility | F30: (determined with square root rule)
A31: Water | C31: =SUM(E3:E26) -> 5566
B32: Y | C32: =SUM(E3:E14) -> 722 | E32: =SQRT(C32/1082) -> 0.8168738
B33: N | C33: =SUM(E15:E26) -> 4844
A34: Wind/Hail | C34: =SUM(D3:D26) -> 6202
B35: Roof 1 | C35: =D3+D6+D9+D12+D15+D18+D21+D24 -> 4354
B36: Roof 2 | C36: =D4+D7+D10+D13+D16+D19+D22+D25 -> 1204
B37: Roof 3 | C37: =D5+D8+D11+D14+D17+D20+D23+D26 -> 644 | E37: =SQRT(C37/1082) -> 0.77148823
A38: Theft | C38: =SUM(G3:G26) -> 1344
B39: Alarm 1 | C39: =SUM(G3:G5)+SUM(G15:G17) -> 203 | E39: =SQRT(C39/1082) -> 0.43314608
B40: Alarm 2 | C40: =SUM(G6:G8)+SUM(G18:G20) -> 587 | E40: =SQRT(C40/1082) -> 0.7365554
B41: Alarm 3 | C41: =SUM(G9:G11)+SUM(G21:G23) -> 389 | E41: =SQRT(C41/1082) -> 0.59959937
B42: Alarm 4 | C42: =SUM(G12:G14)+SUM(G24:G26) -> 165 | E42: =SQRT(C42/1082) -> 0.39050657

Sheet Competitor Information
A1: Apples Insurance Company (35% Market Share)
A3: Water Sensor | B3: Discount Factor | D3: Alarm | E3: Discount Factor | G3: Roof Type | H3: Discount Factor
A4: Y | B4: 0.85 | D4: 1 - None | E4: 1 | G4: 1 - Shingle | H4: 1
A5: N | B5: 1 | D5: 2 - Local | E5: 0.9 | G5: 2 - Hail Resistant Shingle | H5: 0.95
D6: 3 - High Tech | E6: 0.85 | G6: 3 - Solar Panel | H6: 0.9
D7: 4 - Monitored High Tech | E7: 0.8
A10: Bananas Insurance Company (20% Market Share)
A12: Water Sensor | B12: Discount Factor | D12: Alarm | E12: Discount Factor | G12: Roof Type | H12: Discount Factor
A13: Y | B13: 0.9 | D13: 1 - None | E13: 1 | G13: 1 - Shingle | H13: 1
A14: N | B14: 1 | D14: 2 - Local | E14: 0.8 | G14: 2 - Hail Resistant Shingle | H14: 0.85
D15: 3 - High Tech | E15: 0.76 | G15: 3 - Solar Panel | H15: 0.75
D16: 4 - Monitored High Tech | E16: 0.65
A19: Avocado Insurannce Company (10% Market Share)
A21: Water Sensor | B21: Discount Factor | D21: Alarm | E21: Discount Factor | G21: Roof Type | H21: Discount Factor
A22: Y | B22: 0.7 | D22: 1 - None | E22: 1 | G22: 1 - Shingle | H22: 1
A23: N | B23: 1 | D23: 2 - Local | E23: 0.9 | G23: 2 - Hail Resistant Shingle | H23: 1
D24: 3 - High Tech | E24: 0.85 | G24: 3 - Solar Panel | H24: 1
D25: 4 - Monitored High Tech | E25: 0.8
A28: Average (weighted by market share)
A30: Water Sensor | B30: Discount Factor | D30: Alarm | E30: Discount Factor | G30: Roof Type | H30: Discount Factor
A31: Y | B31: =((0.35*B4)+(0.2*B13)+(0.1*B22))/0.65 -> 0.84230769 | D31: 1 - None | E31: =((0.35*E4)+(0.2*E13)+(0.1*E22))/0.65 -> 1 | G31: 1 - Shingle | H31: =((0.35*H4)+(0.2*H13)+(0.1*H22))/0.65 -> 1
A32: N | B32: =((0.35*B5)+(0.2*B14)+(0.1*B23))/0.65 -> 1 | D32: 2 - Local | E32: =((0.35*E5)+(0.2*E14)+(0.1*E23))/0.65 -> 0.86923077 | G32: 2 - Hail Resistant Shingle | H32: =((0.35*H5)+(0.2*H14)+(0.1*H23))/0.65 -> 0.92692308
D33: 3 - High Tech | E33: =((0.35*E6)+(0.2*E15)+(0.1*E24))/0.65 -> 0.82230769 | G33: 3 - Solar Panel | H33: =((0.35*H6)+(0.2*H15)+(0.1*H24))/0.65 -> 0.86923077
D34: 4 - Monitored High Tech | E34: =((0.35*E7)+(0.2*E16)+(0.1*E25))/0.65 -> 0.75384615

Sheet Company Expenses
A1: Expense Category | B1: Yearly Expense | C1: F/V
A2: General Expenses | B2: 35886895 | C2: Fixed
A3: Commission | B3: 29196193 | C3: Variable
A4: Other Acquisition | B4: 21917117 | C4: Fixed
A5: Taxes, Licenses, and Fees | B5: 6998478.7 | C5: Variable

Sheet Discount Calculations
B1: Premiums | C1: Losses | D1: Loss Ratio | E1: Credibility(Claims) | F1: Partial Credibility | H1: Indicated relativity | I1: Complement | J1: Final relativity | L1: Suggested Discount | M1: (1- Discount Factor) | O1: Final Discount | P1: (1- Final Factor)
A2: Water Sensor
A3: Y | B3: =SUM(Premiums!E3:E14) -> 18668679 | C3: =SUM('Losses and LAE'!E3:E14) -> 7216384 | D3: =C3/B3 -> 0.38655033 | E3: ='Claim&Credibility'!C32 -> 722 | F3: ='Claim&Credibility'!E32 -> 0.8168738 | H3: =D3/D4 -> 0.58245816 | I3: ='Competitor Information'!B31 -> 0.84230769 | J3: =(F3*H3)+(1-F3)*(I3) -> 0.63004341 | L3: =1-J3 -> 0.36995659 | M3: =1-L3 -> 0.63004341 | O3: 0.3 | P3: =1-O3 -> 0.7
A4: N (base class) | B4: =SUM(Premiums!E15:E26) -> 74628568 | C4: =SUM('Losses and LAE'!E15:E26) -> 49527502 | D4: =C4/B4 -> 0.66365339 | E4: ='Claim&Credibility'!C33 -> 4844
A6: Alarm
A7: 1 - None (base class) | B7: =SUM(Premiums!G3:G5)+SUM(Premiums!G15:G17) -> 2334944 | C7: =SUM('Losses and LAE'!G3:G5)+SUM('Losses and LAE'!G15:G17) -> 1573992 | D7: =C7/B7 -> 0.67410268 | E7: ='Claim&Credibility'!C39 -> 203 | F7: ='Claim&Credibility'!E39 -> 0.43314608
A8: 2 - Local Alarm | B8: =SUM(Premiums!G6:G8)+SUM(Premiums!G18:G20) -> 9326324 | C8: =SUM('Losses and LAE'!G6:G8)+SUM('Losses and LAE'!G18:G20) -> 5294912 | D8: =C8/B8 -> 0.56773837 | E8: ='Claim&Credibility'!C40 -> 587 | F8: ='Claim&Credibility'!E40 -> 0.7365554 | H8: =D8/D7 -> 0.8422135 | I8: ='Competitor Information'!E32 -> 0.86923077 | J8: =(H8*F8)+(1-F8)*(I8) -> 0.84933105 | L8: =1-J8 -> 0.15066895 | M8: =1-L8 -> 0.84933105 | O8: 0.15 | P8: =1-O8 -> 0.85
A9: 3 - High Tech Local Alarm | B9: =SUM(Premiums!G21:G23)+SUM(Premiums!G9:G11) -> 6997825 | C9: =SUM('Losses and LAE'!G9:G11)+SUM('Losses and LAE'!G21:G23) -> 3265800 | D9: =C9/B9 -> 0.46668786 | E9: ='Claim&Credibility'!C41 -> 389 | F9: ='Claim&Credibility'!E41 -> 0.59959937 | H9: =D9/D7 -> 0.69230976 | I9: ='Competitor Information'!E33 -> 0.82230769 | J9: =(H9*F9)+(1-F9)*(I9) -> 0.74436101 | L9: =1-J9 -> 0.25563899 | M9: =1-L9 -> 0.74436101 | O9: 0.25 | P9: =1-O9 -> 0.75
A10: 4 - Monitored High Tech Alarm | B10: =SUM(Premiums!G12:G14)+SUM(Premiums!G24:G26) -> 4674446 | C10: =SUM('Losses and LAE'!G12:G14)+SUM('Losses and LAE'!G24:G26) -> 1875366 | D10: =C10/B10 -> 0.40119535 | E10: ='Claim&Credibility'!C42 -> 165 | F10: ='Claim&Credibility'!E42 -> 0.39050657 | H10: =D10/D7 -> 0.59515466 | I10: ='Competitor Information'!E34 -> 0.75384615 | J10: =(H10*F10)+(1-F10)*(I10) -> 0.69187608 | L10: =1-J10 -> 0.30812392 | M10: =1-L10 -> 0.69187608 | O10: 0.3 | P10: =1-O10 -> 0.7
A12: Roof
A13: 1 - Composite Shingle (base class) | B13: =SUM(Premiums!D3,Premiums!D6,Premiums!D9,Premiums!D12,Premiums!D15,Premiums!D18,Premiums!D21,Premiums!D24) -> 125958104 | C13: =SUM('Losses and LAE'!D3,'Losses and LAE'!D6,'Losses and LAE'!D9,'Losses and LAE'!D12,'Losses and LAE'!D15,'Losses and LAE'!D18,'Losses and LAE'!D21,'Losses and LAE'!D24,) -> 84085527 | D13: =C13/B13 -> 0.66756742 | E13: ='Claim&Credibility'!C35 -> 4354
A14: 2 - Hail Resistant Shingle | B14: =SUM(Premiums!D4,Premiums!D7,Premiums!D10,Premiums!D13,Premiums!D16,Premiums!D19,Premiums!D22,Premiums!D25) -> 62904433 | C14: =SUM('Losses and LAE'!D4,'Losses and LAE'!D7,'Losses and LAE'!D10,'Losses and LAE'!D13,'Losses and LAE'!D16,'Losses and LAE'!D19,'Losses and LAE'!D22,'Losses and LAE'!D25) -> 33757546 | D14: =C14/B14 -> 0.53664812 | E14: ='Claim&Credibility'!C36 -> 1204 | H14: =D14/D13 -> 0.80388603 | I14: N/A | J14: =H14 -> 0.80388603 | L14: =1-J14 -> 0.19611397 | M14: =1-L14 -> 0.80388603 | O14: 0.2 | P14: =1-O14 -> 0.8
A15: 3 - Solar Panel over Shingle | B15: =SUM(Premiums!D5,Premiums!D8,Premiums!D11,Premiums!D14,Premiums!D17,Premiums!D20,Premiums!D23,Premiums!D26) -> 20990045 | C15: =SUM('Losses and LAE'!D5,'Losses and LAE'!D8,'Losses and LAE'!D11,'Losses and LAE'!D14,'Losses and LAE'!D17,'Losses and LAE'!D20,'Losses and LAE'!D23,'Losses and LAE'!D26) -> 11250721 | D15: =C15/B15 -> 0.53600271 | E15: ='Claim&Credibility'!C37 -> 644 | F15: ='Claim&Credibility'!E37 -> 0.77148823 | H15: =D15/D13 -> 0.80291921 | I15: 1 | J15: =(F15*H15)+(1-F15)*(I15) -> 0.84795449 | L15: =1-J15 -> 0.15204551 | M15: =1-L15 -> 0.84795449 | O15: 0.15 | P15: =1-O15 -> 0.85
A19: Methodology: | H19: Notes:
A21: Credibility: | H21: Credibility:
A22: Data deemed credible when 1082 claims | C22: where: | H22: This sqaure root credibility formula seems to be the standard for ratemaking purposes
A23: Partial credibility determined with formula: | C23: Z = credibility weight | H23: Was given in the packet that 1082 is when credibility is achieved
C24: N = the actual number of observations
C25: = the number of observations to achieve credibility
H26: Complement:
A27: Indicated Relativity: | H27: For most cases the complement used was the weighted average (by market share) of the competitors discounts
A28: The indicated relativity evaluates how a specific subset compares to the baseline average. The formula computes as follows: | H28: A notable exception of this is Roof 3.
A33: Incorporating Credibility: | H33: Preliminary Findings / Talking Points:
A34: Because a small or new risk class may not have enough historical data to be fully statistically reliable, actuaries apply a credibility factor (Z)
A35: This factor assigns a weight to the class's own indicated relativity and balances it with a baseline expected relativity using a factor of 1 - Z | H35: Hail Resistant Shingle:
H36: Apples only offers a 5% discount, Bananas offers 15%, and Avocado offers 0%
H37: Our fully credibile data justifies a 19% discount
A38: where: | H38: By implementing this steep discount we will drastically undercut the market and receive a flood of highly profitable, low risk customers
A39: R weighted = the final, blended relativity factor applied to risk
A40: R indicated = the relativity calculated from local data | H40: Solar Panel over Shingle:
A41: R complement = A broader, more stable baseline figure | H41: Apples offers a 10% discount, Bananas offers 25%, and Avocado offers 0%
A42: Z = credibility factor | H42: Only 644 claims, lacking in credibility
H43: In addition, although data suggests losses are lower for Solar Panel over Shingle, the presence of solar panels will increase the cost of a claim
H44: Making solar panels a riskier choice to insure, especially taking into consideration our lack of data
H45: For these reasons a more conservative R complement of 1 was chosen
H46: This will result in the riskier customers choosing to go to Bananas, but this loss of market share will be compensated for by the inflow of customers
H47: from our large, data backed, Hail Resistant Shingle Discount

Sheet Rebasing Calculations
A1: In order to properly rebase, we need to calculate the premium we would collect under out proposed discount structure
A3: Proposed Premium (Calculated by applying relevant discount factors to premium numbers from last year to see how much premium we would have collected last year with the proposed discount structure)
A4: Discounts | D4: Peril
A5: Water Sensor | B5: Alarm | C5: Roof Type | D5: Wind/Hail | E5: Water | F5: Fire | G5: Theft | H5: Other | I5: Liability
A6: Y | B6: 1 | C6: 1 | D6: {=_xlfn.IFS(Premiums!C3=1,1,Premiums!C3=2, 'Discount Calculations'!$P$14,Premiums!C3=3,'Discount Calculations'!$P$15)*Premiums!D3} -> 2521391 | E6: =IF(Premiums!A3="Y",'Discount Calculations'!$P$3,1)*Premiums!E3 -> 783565.3 | F6: =Premiums!F3 -> 836869 | G6: {=_xlfn.IFS(Premiums!B3=1,1, Premiums!B3=2,'Discount Calculations'!$P$8,Premiums!B3=3,'Discount Calculations'!$P$9,Premiums!B3=4,'Discount Calculations'!$P$10)*Premiums!G3} -> 280509 | H6: =Premiums!H3 -> 562613 | I6: =Premiums!I3 -> 279939
A7: Y | B7: 1 | C7: 2 | D7: {=_xlfn.IFS(Premiums!C4=1,1,Premiums!C4=2, 'Discount Calculations'!$P$14,Premiums!C4=3,'Discount Calculations'!$P$15)*Premiums!D4} -> 1012032 | E7: =IF(Premiums!A4="Y",'Discount Calculations'!$P$3,1)*Premiums!E4 -> 391085.1 | F7: =Premiums!F4 -> 418395 | G7: {=_xlfn.IFS(Premiums!B4=1,1, Premiums!B4=2,'Discount Calculations'!$P$8,Premiums!B4=3,'Discount Calculations'!$P$9,Premiums!B4=4,'Discount Calculations'!$P$10)*Premiums!G4} -> 139599 | H7: =Premiums!H4 -> 280331 | I7: =Premiums!I4 -> 139547
A8: Y | B8: 1 | C8: 3 | D8: {=_xlfn.IFS(Premiums!C5=1,1,Premiums!C5=2, 'Discount Calculations'!$P$14,Premiums!C5=3,'Discount Calculations'!$P$15)*Premiums!D5} -> 358558.9 | E8: =IF(Premiums!A5="Y",'Discount Calculations'!$P$3,1)*Premiums!E5 -> 130412.1 | F8: =Premiums!F5 -> 139468 | G8: {=_xlfn.IFS(Premiums!B5=1,1, Premiums!B5=2,'Discount Calculations'!$P$8,Premiums!B5=3,'Discount Calculations'!$P$9,Premiums!B5=4,'Discount Calculations'!$P$10)*Premiums!G5} -> 46769 | H8: =Premiums!H5 -> 93730 | I8: =Premiums!I5 -> 46508
A9: Y | B9: 2 | C9: 1 | D9: {=_xlfn.IFS(Premiums!C6=1,1,Premiums!C6=2, 'Discount Calculations'!$P$14,Premiums!C6=3,'Discount Calculations'!$P$15)*Premiums!D6} -> 10104346 | E9: =IF(Premiums!A6="Y",'Discount Calculations'!$P$3,1)*Premiums!E6 -> 3141889.8 | F9: =Premiums!F6 -> 3371550 | G9: {=_xlfn.IFS(Premiums!B6=1,1, Premiums!B6=2,'Discount Calculations'!$P$8,Premiums!B6=3,'Discount Calculations'!$P$9,Premiums!B6=4,'Discount Calculations'!$P$10)*Premiums!G6} -> 956129.3 | H9: =Premiums!H6 -> 2245941 | I9: =Premiums!I6 -> 1117251
A10: Y | B10: 2 | C10: 2 | D10: {=_xlfn.IFS(Premiums!C7=1,1,Premiums!C7=2, 'Discount Calculations'!$P$14,Premiums!C7=3,'Discount Calculations'!$P$15)*Premiums!D7} -> 4030308.8 | E10: =IF(Premiums!A7="Y",'Discount Calculations'!$P$3,1)*Premiums!E7 -> 1565563.3 | F10: =Premiums!F7 -> 1679608 | G10: {=_xlfn.IFS(Premiums!B7=1,1, Premiums!B7=2,'Discount Calculations'!$P$8,Premiums!B7=3,'Discount Calculations'!$P$9,Premiums!B7=4,'Discount Calculations'!$P$10)*Premiums!G7} -> 475135.55 | H10: =Premiums!H7 -> 1118357 | I10: =Premiums!I7 -> 562623
A11: Y | B11: 2 | C11: 3 | D11: {=_xlfn.IFS(Premiums!C8=1,1,Premiums!C8=2, 'Discount Calculations'!$P$14,Premiums!C8=3,'Discount Calculations'!$P$15)*Premiums!D8} -> 1422946.8 | E11: =IF(Premiums!A8="Y",'Discount Calculations'!$P$3,1)*Premiums!E8 -> 525107.1 | F11: =Premiums!F8 -> 560756 | G11: {=_xlfn.IFS(Premiums!B8=1,1, Premiums!B8=2,'Discount Calculations'!$P$8,Premiums!B8=3,'Discount Calculations'!$P$9,Premiums!B8=4,'Discount Calculations'!$P$10)*Premiums!G8} -> 159289.15 | H11: =Premiums!H8 -> 371994 | I11: =Premiums!I8 -> 186625
A12: Y | B12: 3 | C12: 1 | D12: {=_xlfn.IFS(Premiums!C9=1,1,Premiums!C9=2, 'Discount Calculations'!$P$14,Premiums!C9=3,'Discount Calculations'!$P$15)*Premiums!D9} -> 7574980 | E12: =IF(Premiums!A9="Y",'Discount Calculations'!$P$3,1)*Premiums!E9 -> 2359500.5 | F12: =Premiums!F9 -> 2522123 | G12: {=_xlfn.IFS(Premiums!B9=1,1, Premiums!B9=2,'Discount Calculations'!$P$8,Premiums!B9=3,'Discount Calculations'!$P$9,Premiums!B9=4,'Discount Calculations'!$P$10)*Premiums!G9} -> 627560.25 | H12: =Premiums!H9 -> 1679515 | I12: =Premiums!I9 -> 836211
A13: Y | B13: 3 | C13: 2 | D13: {=_xlfn.IFS(Premiums!C10=1,1,Premiums!C10=2, 'Discount Calculations'!$P$14,Premiums!C10=3,'Discount Calculations'!$P$15)*Premiums!D10} -> 3024093.6 | E13: =IF(Premiums!A10="Y",'Discount Calculations'!$P$3,1)*Premiums!E10 -> 1175006.7 | F13: =Premiums!F10 -> 1261442 | G13: {=_xlfn.IFS(Premiums!B10=1,1, Premiums!B10=2,'Discount Calculations'!$P$8,Premiums!B10=3,'Discount Calculations'!$P$9,Premiums!B10=4,'Discount Calculations'!$P$10)*Premiums!G10} -> 314993.25 | H13: =Premiums!H10 -> 842585 | I13: =Premiums!I10 -> 417989
A14: Y | B14: 3 | C14: 3 | D14: {=_xlfn.IFS(Premiums!C11=1,1,Premiums!C11=2, 'Discount Calculations'!$P$14,Premiums!C11=3,'Discount Calculations'!$P$15)*Premiums!D11} -> 1073653.7 | E14: =IF(Premiums!A11="Y",'Discount Calculations'!$P$3,1)*Premiums!E11 -> 392284.2 | F14: =Premiums!F11 -> 420443 | G14: {=_xlfn.IFS(Premiums!B11=1,1, Premiums!B11=2,'Discount Calculations'!$P$8,Premiums!B11=3,'Discount Calculations'!$P$9,Premiums!B11=4,'Discount Calculations'!$P$10)*Premiums!G11} -> 104769 | H14: =Premiums!H11 -> 278698 | I14: =Premiums!I11 -> 140219
A15: Y | B15: 4 | C15: 1 | D15: {=_xlfn.IFS(Premiums!C12=1,1,Premiums!C12=2, 'Discount Calculations'!$P$14,Premiums!C12=3,'Discount Calculations'!$P$15)*Premiums!D12} -> 5055839 | E15: =IF(Premiums!A12="Y",'Discount Calculations'!$P$3,1)*Premiums!E12 -> 1562358.7 | F15: =Premiums!F12 -> 1683337 | G15: {=_xlfn.IFS(Premiums!B12=1,1, Premiums!B12=2,'Discount Calculations'!$P$8,Premiums!B12=3,'Discount Calculations'!$P$9,Premiums!B12=4,'Discount Calculations'!$P$10)*Premiums!G12} -> 391239.1 | H15: =Premiums!H12 -> 1116047 | I15: =Premiums!I12 -> 558250
A16: Y | B16: 4 | C16: 2 | D16: {=_xlfn.IFS(Premiums!C13=1,1,Premiums!C13=2, 'Discount Calculations'!$P$14,Premiums!C13=3,'Discount Calculations'!$P$15)*Premiums!D13} -> 2023866.4 | E16: =IF(Premiums!A13="Y",'Discount Calculations'!$P$3,1)*Premiums!E13 -> 780720.5 | F16: =Premiums!F13 -> 837676 | G16: {=_xlfn.IFS(Premiums!B13=1,1, Premiums!B13=2,'Discount Calculations'!$P$8,Premiums!B13=3,'Discount Calculations'!$P$9,Premiums!B13=4,'Discount Calculations'!$P$10)*Premiums!G13} -> 195627.6 | H16: =Premiums!H13 -> 560065 | I16: =Premiums!I13 -> 281288
A17: Y | B17: 4 | C17: 3 | D17: {=_xlfn.IFS(Premiums!C14=1,1,Premiums!C14=2, 'Discount Calculations'!$P$14,Premiums!C14=3,'Discount Calculations'!$P$15)*Premiums!D14} -> 715785 | E17: =IF(Premiums!A14="Y",'Discount Calculations'!$P$3,1)*Premiums!E14 -> 260582 | F17: =Premiums!F14 -> 278614 | G17: {=_xlfn.IFS(Premiums!B14=1,1, Premiums!B14=2,'Discount Calculations'!$P$8,Premiums!B14=3,'Discount Calculations'!$P$9,Premiums!B14=4,'Discount Calculations'!$P$10)*Premiums!G14} -> 65114.7 | H17: =Premiums!H14 -> 186793 | I17: =Premiums!I14 -> 93263
... A29: N | B29: 4 | C29: 3 | D29: {=_xlfn.IFS(Premiums!C26=1,1,Premiums!C26=2, 'Discount Calculations'!$P$14,Premiums!C26=3,'Discount Calculations'!$P$15)*Premiums!D26} -> 2857721.2 | E29: =IF(Premiums!A26="Y",'Discount Calculations'!$P$3,1)*Premiums!E26 -> 1495265 | F29: =Premiums!F26 -> 1125110 | G29: {=_xlfn.IFS(Premiums!B26=1,1, Premiums!B26=2,'Discount Calculations'!$P$8,Premiums!B26=3,'Discount Calculations'!$P$9,Premiums!B26=4,'Discount Calculations'!$P$10)*Premiums!G26} -> 261989.7 | H29: =Premiums!H26 -> 747189 | I29: =Premiums!I26 -> 373847
D30: =SUM(D6:D29) -> 1.9412319e+08 | E30: =SUM(E6:E29) -> 87696643 | F30: =SUM(F6:F29) -> 70067125 | G30: =SUM(G6:G29) -> 18782800 | H30: =SUM(H6:H29) -> 46690073 | I30: =SUM(I6:I29) -> 23324942
A32: Rebalancing Factors (by peril) (this stops the fire liability and other categories from being needlessly inflated)
A33: Water:
A34: Proposed Premium: | B34: =E30 -> 87696643
A35: Current Premium: | B35: =Premiums!E27 -> 93297247
A36: Rebalance Factor: | B36: =B35/B34 -> 1.0638634
A38: Wind/Hail:
A39: Proposed Premium: | B39: =D30 -> 1.9412319e+08
A40: Current Premium: | B40: =Premiums!D27 -> 209852582
A41: Rebalance Factor: | B41: =B40/B39 -> 1.0810279
A43: Theft
A44: Proposed Premium: | B44: =G30 -> 18782800
A45: Current Premium: | B45: =Premiums!G27 -> 23333539
A46: Rebalance Factor: | B46: =B45/B44 -> 1.2422822
